CHANGES.txt
LICENSE.txt
MANIFEST.in
README.md
setup.py
foundationform/__init__.py
foundationform/__init__.pyc
foundationform/models.py
foundationform/models.pyc
foundationform/runtests.py
foundationform/tests.py
foundationform.egg-info/PKG-INFO
foundationform.egg-info/SOURCES.txt
foundationform.egg-info/dependency_links.txt
foundationform.egg-info/top_level.txt
foundationform/templates/foundationform/_foundation_form_field.html
foundationform/templates/foundationform/foundation_form.html
foundationform/templates/foundationform/foundation_formset.html
foundationform/templatetags/__init__.py
foundationform/templatetags/__init__.pyc
foundationform/templatetags/foundation.py
foundationform/templatetags/foundation.pyc