Metadata-Version: 1.1
Name: foundationform
Version: 0.2
Summary: Reusable Django app for display zurb foundation forms
Home-page: http://github.com/TigorC/django-foundation-form
Author: Igor Tokarev
Author-email: TigorC@gmail.com
License: See LICENSE.txt
Platform: UNKNOWN
Classifier: Programming Language :: Python
Classifier: Topic :: Software Development :: Libraries :: Python Modules
Classifier: Framework :: Django
Classifier: Environment :: Web Environment
